__init__.py
semi_pyramid_generator.py
semipyramidgenerator-0.0.1.dist-info/LICENSE.txt
semipyramidgenerator-0.0.1.dist-info/METADATA
semipyramidgenerator-0.0.1.dist-info/WHEEL
semipyramidgenerator-0.0.1.dist-info/top_level.txt
semipyramidgenerator-0.0.1.dist-info/RECORD
